{
	"name": "SourceDataset_dgb",
	"properties": {
		"linkedServiceName": {
			"referenceName": "AzureBlobStorage_adfdevlopment",
			"type": "LinkedServiceReference"
		},
		"annotations": [],
		"type": "DelimitedText",
		"typeProperties": {
			"location": {
				"type": "AzureBlobStorageLocation",
				"fileName": "Request_new software to IT .txt",
				"container": "rawzone"
			},
			"columnDelimiter": ",",
			"rowDelimiter": "\n",
			"escapeChar": "\\",
			"firstRowAsHeader": true,
			"quoteChar": ""
		},
		"schema": [
			{
				"type": "String"
			}
		]
	}
}